CommonMode/__init__.py
CommonMode/main.py
RSAattack-0.1.dist-info/LICENSE
RSAattack-0.1.dist-info/METADATA
RSAattack-0.1.dist-info/WHEEL
RSAattack-0.1.dist-info/top_level.txt
RSAattack-0.1.dist-info/RECORD
